trytond/modules/health_inpatient/COPYING
trytond/modules/health_inpatient/MANIFEST.in
trytond/modules/health_inpatient/README.rst
trytond/modules/health_inpatient/__init__.py
trytond/modules/health_inpatient/data/health_inpatient_sequence.xml
trytond/modules/health_inpatient/data/inpatient_diets.xml
trytond/modules/health_inpatient/data/messages/messages.xml
trytond/modules/health_inpatient/exceptions.py
trytond/modules/health_inpatient/health.py
trytond/modules/health_inpatient/health_inpatient.py
trytond/modules/health_inpatient/health_inpatient_report.xml
trytond/modules/health_inpatient/health_inpatient_view.xml
trytond/modules/health_inpatient/icons/cancel.svg
trytond/modules/health_inpatient/icons/go-home.svg
trytond/modules/health_inpatient/icons/hospital.svg
trytond/modules/health_inpatient/icons/meals.svg
trytond/modules/health_inpatient/icons/ok.svg
trytond/modules/health_inpatient/locale/ar.po
trytond/modules/health_inpatient/locale/de.po
trytond/modules/health_inpatient/locale/el.po
trytond/modules/health_inpatient/locale/eo.po
trytond/modules/health_inpatient/locale/es.po
trytond/modules/health_inpatient/locale/fr.po
trytond/modules/health_inpatient/locale/health_inpatient.pot
trytond/modules/health_inpatient/locale/it_IT.po
trytond/modules/health_inpatient/locale/ja_JP.po
trytond/modules/health_inpatient/locale/ka.po
trytond/modules/health_inpatient/locale/lo.po
trytond/modules/health_inpatient/locale/pt_BR.po
trytond/modules/health_inpatient/locale/sv.po
trytond/modules/health_inpatient/locale/tr.po
trytond/modules/health_inpatient/locale/uk.po
trytond/modules/health_inpatient/locale/zh_CN.po
trytond/modules/health_inpatient/pyproject.toml
trytond/modules/health_inpatient/report/round_report.fodt
trytond/modules/health_inpatient/security/access_rights.xml
trytond/modules/health_inpatient/sequences.py
trytond/modules/health_inpatient/tests/__init__.py
trytond/modules/health_inpatient/tests/test_health_inpatient.py
gnuhealth_inpatient-5.0.2.dist-info/METADATA
gnuhealth_inpatient-5.0.2.dist-info/WHEEL
gnuhealth_inpatient-5.0.2.dist-info/licenses/COPYING
gnuhealth_inpatient-5.0.2.dist-info/RECORD
